envenom/__init__.py
envenom/entries.py
envenom/environment.py
envenom/errors.py
envenom/examples/__init__.py
envenom/examples/advanced/__init__.py
envenom/examples/advanced/dataclasses.py
envenom/examples/advanced/enums.py
envenom/examples/advanced/integrations/__init__.py
envenom/examples/advanced/integrations/django-settings.py
envenom/examples/advanced/integrations/fastapi.py
envenom/examples/advanced/integrations/flask.py
envenom/examples/advanced/singletons.py
envenom/examples/advanced/uuids.py
envenom/examples/files.py
envenom/examples/namespaces.py
envenom/examples/parsers.py
envenom/examples/quickstart.py
envenom/parsers.py
envenom/py.typed
envenom/vars.py
envenom-3.2.2.post1.dist-info/LICENSE
envenom-3.2.2.post1.dist-info/METADATA
envenom-3.2.2.post1.dist-info/WHEEL
envenom-3.2.2.post1.dist-info/RECORD
