Metadata-Version: 2.3
Name: envenom
Version: 3.2.2.post1
Summary: An elegant application configurator for the more civilized age
License: GPL-3.0-or-later
Keywords: env,environment,config,configuration
Author: Artur Ciesielski
Author-email: artur.ciesielski@gmail.com
Requires-Python: >=3.12,<4.0
Classifier: Development Status :: 5 - Production/Stable
Classifier: Intended Audience :: Developers
Classifier: Operating System :: OS Independent
Classifier: Topic :: Software Development :: Libraries :: Application Frameworks
Classifier: Topic :: Software Development :: Libraries :: Python Modules
Classifier: Typing :: Typed
Requires-Dist: encrustable (>=1.0.0)
Project-URL: Documentation, https://arcanery.gitlab.io/python/envenom/
Project-URL: Homepage, https://gitlab.com/arcanery/python/envenom
Project-URL: Repository, https://gitlab.com/arcanery/python/envenom
